rlmmyelintek/__init__.py
rlmmyelintek/_rlmwrapper.so
rlmmyelintek/rlmwrapper.py
rlmmyelintek-1.1.dist-info/DESCRIPTION.rst
rlmmyelintek-1.1.dist-info/METADATA
rlmmyelintek-1.1.dist-info/RECORD
rlmmyelintek-1.1.dist-info/WHEEL
rlmmyelintek-1.1.dist-info/metadata.json
rlmmyelintek-1.1.dist-info/top_level.txt
