Metadata-Version: 2.0
Name: rlmmyelintek
Version: 1.1
Summary: This is a pip wheel of the setup
Home-page: UNKNOWN
Author: Teyen Liu
Author-email: Teyen.Liu@itri.org.tw
License: UNKNOWN
Platform: UNKNOWN
